envguard_python/__init__.py
envguard_python/exceptions.py
envguard_python/types.py
envguard_python/validator.py
envguard_python-0.1.5.dist-info/METADATA
envguard_python-0.1.5.dist-info/WHEEL
envguard_python-0.1.5.dist-info/RECORD
