Metadata-Version: 2.4
Name: envguard-python
Version: 0.1.5
Summary: A Python utility for robust serverless environment variable validation using Pydantic
Project-URL: Homepage, https://github.com/cschanhniem/EnvGuard
Project-URL: Documentation, https://github.com/cschanhniem/EnvGuard/tree/main/packages/envguard-python#readme
Project-URL: Repository, https://github.com/cschanhniem/EnvGuard.git
Project-URL: Issues, https://github.com/cschanhniem/EnvGuard/issues
Author-email: EnvGuard Contributors <envguard@example.com>
License: MIT
Keywords: aws-lambda,azure-functions,configuration,environment-variables,google-cloud-functions,pydantic,serverless,validation
Classifier: Development Status :: 3 - Alpha
Classifier: Framework :: Pydantic
Classifier: Intended Audience :: Developers
Classifier: License :: OSI Approved :: MIT License
Classifier: Operating System :: OS Independent
Classifier: Programming Language :: Python :: 3
Classifier: Programming Language :: Python :: 3.8
Classifier: Programming Language :: Python :: 3.9
Classifier: Programming Language :: Python :: 3.10
Classifier: Programming Language :: Python :: 3.11
Classifier: Topic :: Software Development :: Libraries :: Python Modules
Classifier: Typing :: Typed
Requires-Python: >=3.8
Requires-Dist: email-validator>=2.0.0
Requires-Dist: pydantic>=2.0.0
Requires-Dist: typing-extensions>=4.5.0
Provides-Extra: dev
Requires-Dist: black>=23.3.0; extra == 'dev'
Requires-Dist: mypy>=1.3.0; extra == 'dev'
Requires-Dist: ruff>=0.0.270; extra == 'dev'
Requires-Dist: types-setuptools>=68.0.0; extra == 'dev'
Provides-Extra: test
Requires-Dist: pytest-cov>=4.0.0; extra == 'test'
Requires-Dist: pytest-mock>=3.10.0; extra == 'test'
Requires-Dist: pytest>=7.0.0; extra == 'test'
